osmpy/__init__.py
osmpy/core.py
osmpy/queries.py
osmpy-0.2.0.dist-info/WHEEL
osmpy-0.2.0.dist-info/METADATA
osmpy-0.2.0.dist-info/RECORD
