Metadata-Version: 2.1
Name: osmpy
Version: 0.2.0
Summary: Powerfull wrapper around OSM Overpass Turbo to query regions of any size and shape
Home-page: https://github.com/JoaoCarabetta/osmpy
License: AM-331-A3 Licencia de Software
Author: Joao Carabetta
Author-email: joao.carabetta@gmail.com
Requires-Python: >=3.6,<4.0
Classifier: License :: Other/Proprietary License
Classifier: Programming Language :: Python :: 3
Classifier: Programming Language :: Python :: 3.6
Classifier: Programming Language :: Python :: 3.7
Classifier: Programming Language :: Python :: 3.8
Classifier: Programming Language :: Python :: 3.9
Classifier: Topic :: Software Development :: Build Tools
Classifier: Topic :: Software Development :: Libraries :: Python Modules
Requires-Dist: geojson (==2.5.0)
Requires-Dist: pandas (>=1.0.0,<2.0.0)
Requires-Dist: pyproj
Requires-Dist: requests (==2.23.0)
Requires-Dist: retry
Requires-Dist: shapely (==1.7.0)
Project-URL: Repository, https://github.com/JoaoCarabetta/osmpy
